eugene/__init__.py
eugene/_settings.py
eugene/conftest.py
eugene/dataload/__init__.py
eugene/dataload/_augment.py
eugene/dataload/_utils.py
eugene/evaluate/__init__.py
eugene/evaluate/_evaluate.py
eugene/evaluate/_predict.py
eugene/evaluate/_utils.py
eugene/evaluate/metrics/__init__.py
eugene/evaluate/metrics/_binary_classification.py
eugene/evaluate/metrics/_multiclass_classification.py
eugene/evaluate/metrics/_profile_prediction.py
eugene/evaluate/metrics/_regression.py
eugene/experimental/_AdverserialModule.py
eugene/experimental/_AugmentModule.py
eugene/experimental/_GenerativeModule.py
eugene/experimental/_LanguageModule.py
eugene/experimental/_hyperopt_wandb.py
eugene/experimental/_language_models.py
eugene/experimental/_preprocess.py
eugene/interpret/__init__.py
eugene/interpret/_attribute.py
eugene/interpret/_filters.py
eugene/interpret/_generative.py
eugene/interpret/_gia.py
eugene/models/_ProfileModule.py
eugene/models/_SequenceModule.py
eugene/models/__init__.py
eugene/models/_utils.py
eugene/models/base/__init__.py
eugene/models/base/_blocks.py
eugene/models/base/_initializers.py
eugene/models/base/_layers.py
eugene/models/base/_losses.py
eugene/models/base/_metrics.py
eugene/models/base/_module.py
eugene/models/base/_optimizers.py
eugene/models/base/_regularizers.py
eugene/models/base/_schedulers.py
eugene/models/base/_towers.py
eugene/models/base/_utils.py
eugene/models/zoo/__init__.py
eugene/models/zoo/_basic_models.py
eugene/models/zoo/_cre_activity_predictors.py
eugene/models/zoo/_profile_predictors.py
eugene/models/zoo/_regulatory_classifiers.py
eugene/models/zoo/_single_cell_predictors.py
eugene/models/zoo/_tf_binding_predictors.py
eugene/plot/__init__.py
eugene/plot/_catplot.py
eugene/plot/_classification.py
eugene/plot/_experimental.py
eugene/plot/_gia.py
eugene/plot/_regression.py
eugene/plot/_seq.py
eugene/plot/_summary.py
eugene/plot/_training.py
eugene/plot/_utils.py
eugene/preprocess/__init__.py
eugene/preprocess/_seqdata.py
eugene_tools-0.1.2.dist-info/LICENSE
eugene_tools-0.1.2.dist-info/METADATA
eugene_tools-0.1.2.dist-info/WHEEL
eugene_tools-0.1.2.dist-info/RECORD
