Metadata-Version: 2.1
Name: eugene-tools
Version: 0.1.2
Summary: Elucidating the Utility of Genomic Elements with Neural Nets
Author: adamklie
Author-email: aklie@ucsd.edu
Requires-Python: >=3.9,<3.11
Classifier: Programming Language :: Python :: 3
Classifier: Programming Language :: Python :: 3.9
Classifier: Programming Language :: Python :: 3.10
Provides-Extra: docs
Requires-Dist: Sphinx[docs] (>=6.2.1,<7.0.0) ; extra == "docs"
Requires-Dist: dask_ml (==2023.3.24)
Requires-Dist: einops (==0.6.1)
Requires-Dist: graph-part (>=0.1.2,<0.2.0)
Requires-Dist: matplotlib (>=3.6.2,<4.0.0)
Requires-Dist: motifdata (>=0.1.0,<0.2.0)
Requires-Dist: myst-parser[docs] (>=2.0.0,<3.0.0) ; extra == "docs"
Requires-Dist: nbsphinx[docs] (>=0.9.2,<0.10.0) ; extra == "docs"
Requires-Dist: pandoc[docs] (>=2.3,<3.0) ; extra == "docs"
Requires-Dist: pytorch-lightning (>=2.0.0,<3.0.0)
Requires-Dist: scikit-learn (==1.2.0)
Requires-Dist: seaborn (>=0.12.0,<0.13.0)
Requires-Dist: seqdata (>=0.1.1,<0.2.0)
Requires-Dist: seqdatasets (>=0.1.0,<0.2.0)
Requires-Dist: seqexplainer (>=0.1.0,<0.2.0)
Requires-Dist: seqpro (>=0.1.1,<0.2.0)
Requires-Dist: sphinx-autobuild[docs] (==2021.3.14) ; extra == "docs"
Requires-Dist: sphinx-autodoc-typehints[docs] (>=1.21.1,<2.0.0) ; extra == "docs"
Requires-Dist: sphinx-rtd-theme[docs] (>=1.2.2,<2.0.0) ; extra == "docs"
Requires-Dist: sphinxcontrib-apidoc[docs] (>=0.3.0,<0.4.0) ; extra == "docs"
Requires-Dist: tensorboard (==2.11.2)
Requires-Dist: torch (>=1.12.0)
Requires-Dist: torchinfo (==1.8.0)
